<?xml version="1.0" encoding="utf-8"?>
<extension version="2.5" type="plugin" group="rb_ecommerceprocessor" method="upgrade">
    <name>plg_rb_ecommerceprocessor_netcash</name>
    <version>0.9.1</version>
    <creationDate>Jul 2013</creationDate>
    <author>Team PayInvoice</author>
    <authorEmail>support+payinvoice@readybytes.in</authorEmail>
    <authorUrl>http://www.readybytes.net/payinvoice.html</authorUrl>
    <copyright>2009-14 Ready Bytes Software Labs Pvt. Ltd.</copyright>
    <license>GNU General Public License v2</license>
    <description>PLG_RB_ECOMMERCEPROCESSOR_NETCASH_DESCRIPTION</description>
	<files>
		<filename plugin="netcash">netcash.php</filename>
		<filename>index.html</filename>
		<folder>processors</folder>
	</files>
	
	<languages>
		<language tag="en-GB">en-GB.plg_rb_ecommerceprocessor_netcash.ini</language>
		<language tag="en-GB">en-GB.plg_rb_ecommerceprocessor_netcash.sys.ini</language>
	</languages>
	
	<config>
	</config>

<alias>rb-netcash</alias>
<version_number>0.9.1</version_number>
<version_name>NetCash 0.9</version_name>
</extension>

